redisdecor-0.1.12.7.dist-info/WHEEL
redisdecor-0.1.12.7.dist-info/LICENSE
redisdecor-0.1.12.7.dist-info/RECORD
redisdecor-0.1.12.7.dist-info/top_level.txt
redisdecor-0.1.12.7.dist-info/METADATA
redisdecor/utils.py
redisdecor/client.py
redisdecor/decorator.py
redisdecor/utils.cpython-311-x86_64-linux-gnu.so
redisdecor/__init__.py
redisdecor/utils.c
redisdecor/logs.py
redisdecor/utils.pxd
