Metadata-Version: 2.1
Name: redisdecor
Version: 0.1.12.7
Summary: Provides decorators to cache/update/delete results to/from Redis.
Home-page: https://github.com/AresJef/RedisDecor
Author: Jiefu Chen
Author-email: keppa1991@163.com
License: MIT license, BSD 3-Clause
Keywords: redis,decorator,cache,update,delete
Classifier: Programming Language :: Python :: 3
Classifier: Operating System :: Unix
Classifier: Operating System :: MacOS :: MacOS X
Classifier: Operating System :: Microsoft :: Windows
Requires-Python: >=3.10
License-File: LICENSE
Requires-Dist: Cython ==3.0.4
Requires-Dist: hiredis >=2.2.3
Requires-Dist: redis >=4.5.5
Requires-Dist: serializor >=0.1.12.8
